matildapeak/chronicler_transmitter.py
matildapeak_chronicler_transmitter-2019.3.dist-info/METADATA
matildapeak_chronicler_transmitter-2019.3.dist-info/WHEEL
matildapeak_chronicler_transmitter-2019.3.dist-info/top_level.txt
matildapeak_chronicler_transmitter-2019.3.dist-info/RECORD
