Metadata-Version: 2.1
Name: matildapeak-chronicler-transmitter
Version: 2019.3
Summary: Utilities for Chronicler event delivery
Home-page: https://gitlab.com/matilda.peak/chronicler-transmitter
Author: Alan Christie
Author-email: alan.christie@matildapeak.com
License: MIT
Keywords: protobuf,chronicler
Platform: any
Classifier: Development Status :: 5 - Production/Stable
Classifier: Environment :: Other Environment
Classifier: Intended Audience :: Developers
Classifier: License :: OSI Approved :: MIT License
Classifier: Programming Language :: Python :: 3.7
Classifier: Topic :: Software Development :: Libraries :: Python Modules
Classifier: Operating System :: POSIX :: Linux
Requires-Python: >=3.7, <4
Requires-Dist: requests (<3.0.0,>=2.22.0)
